get_current_time/__init__.py
get_current_time/server.py
get_current_time_mcp-0.1.0.dist-info/METADATA
get_current_time_mcp-0.1.0.dist-info/WHEEL
get_current_time_mcp-0.1.0.dist-info/entry_points.txt
get_current_time_mcp-0.1.0.dist-info/top_level.txt
get_current_time_mcp-0.1.0.dist-info/RECORD
